animetime.py
animetime-0.2.dist-info/METADATA
animetime-0.2.dist-info/WHEEL
animetime-0.2.dist-info/licenses/LICENSE
animetime-0.2.dist-info/RECORD
