Metadata-Version: 2.1
Name: animetime
Version: 0.2
Summary: A module to manage and track your favourites animes and series
Project-URL: Github, https://github.com/swarthur/animetime
Project-URL: Bug, https://github.com/swarthur/animetime/issues
Author: swarthur
License-Expression: MIT
License-File: LICENSE
Classifier: License :: OSI Approved :: MIT License
Classifier: Operating System :: OS Independent
Classifier: Programming Language :: Python :: 3
Requires-Python: >=3.11
Requires-Dist: animedata
